{
  "$type": "RPG.GameCore.RtLevelGroupInfo",
  "GroupName": "MainMission2022201_1",
  "Category": "Mission",
  "LevelGraph": "Config/Level/GroupGraph/F10201001/Group_F10201001_G238.json",
  "AreaAnchorName": "LevelArea_P10201_F10201001_G238",
  "SaveType": "Reset",
  "IsPendedUnload": true,
  "OwnerMainMissionID": 2022201,
  "ValueSource": {},
  "ConflictIDList": [],
  "IsHoyoGroup": true,
  "ConflictWhiteList": [],
  "TagContainer": {
    "List": [
      {
        "Tag": "Group.TrailblazeContinuance.240to250XianZhou",
        "TagHash": -357934452
      }
    ]
  },
  "AnchorList": [],
  "MonsterList": [],
  "PropList": [
    {
      "PropID": 100,
      "ValueSource": {},
      "CampID": 4,
      "CustomTriggerMap": {},
      "CustomTriggerMapV2": {
        "MissionTrigger": {
          "Shape": "Box",
          "Radius": 2,
          "DimX": 15,
          "DimY": 5,
          "DimZ": 15,
          "PointList": []
        }
      },
      "BridgeStateRotations": [],
      "StateConfigs": [],
      "DialogueGroups": [],
      "TalkDialogGroupIDList": [],
      "ServerInteractVerificationIDList": [],
      "DialogueTriggerSkipSpecifiedFakeAvatarList": [],
      "CameraCenterEntityList": [],
      "SpawnConfig": {
        "EntitySpawnConfig": {}
      },
      "Name": "Prop1",
      "ID": 300001,
      "PosX": -57.71,
      "PosY": -1.031649,
      "PosZ": -63.25
    },
    {
      "PropID": 102253,
      "ValueSource": {},
      "CampID": 4,
      "CustomTriggerMap": {},
      "CustomTriggerMapV2": {},
      "BridgeStateRotations": [],
      "StateConfigs": [],
      "DialogueGroups": [],
      "TalkDialogGroupIDList": [],
      "ServerInteractVerificationIDList": [],
      "DialogueTriggerSkipSpecifiedFakeAvatarList": [],
      "CameraCenterEntityList": [],
      "SpawnConfig": {
        "EntitySpawnConfig": {}
      },
      "Name": "Prop2",
      "ID": 300002,
      "PosX": -53.559,
      "PosY": -0.869,
      "PosZ": -67.942
    }
  ],
  "DistrictList": [],
  "WaypointList": [],
  "PathwayList": [],
  "BattleAreaList": [],
  "NPCList": [
    {
      "NPCID": 1210,
      "ValueSource": {},
      "DialogueGroups": [],
      "ServerInteractVerificationIDList": [],
      "DefaultLookAtMode": "Closed",
      "BoardShowList": [],
      "TalkDialogGroupIDList": [],
      "DefaultIdleFreeStyleMotionID": 312090222,
      "InitialHiddenNodeList": [],
      "Dialog": {
        "LevelGraph": "Config/Level/NPCDialogue/P10201/F10201001_G238/DialogueMain_F10201001_G238_N400001.json",
        "PackList": []
      },
      "DialogueTriggerSkipSpecifiedFakeAvatarList": [],
      "OverrideReplaceMaterialKeyList": [],
      "CameraCenterEntityList": [],
      "SpawnConfig": {
        "EntitySpawnConfig": {}
      },
      "TriggerValidGuest": {},
      "Name": "NPC1",
      "RotY": 216.9623,
      "ID": 400001,
      "PosX": -60.03,
      "PosY": -1.031814,
      "PosZ": -60.94
    },
    {
      "NPCID": 12135,
      "ValueSource": {},
      "DialogueGroups": [],
      "ServerInteractVerificationIDList": [],
      "BoardShowList": [],
      "TalkDialogGroupIDList": [],
      "DefaultIdleFreeStyleMotionID": 100010000,
      "InitialHiddenNodeList": [],
      "DialogueTriggerSkipSpecifiedFakeAvatarList": [],
      "OverrideReplaceMaterialKeyList": [],
      "CameraCenterEntityList": [],
      "SpawnConfig": {
        "EntitySpawnConfig": {}
      },
      "TriggerValidGuest": {},
      "Name": "NPC2",
      "ID": 400002,
      "PosX": -68.567,
      "PosY": -1.012485,
      "PosZ": -60.343
    },
    {
      "NPCID": 12236,
      "ValueSource": {},
      "DialogueGroups": [],
      "ServerInteractVerificationIDList": [],
      "BoardShowList": [],
      "TalkDialogGroupIDList": [],
      "DefaultIdleFreeStyleMotionID": 100020000,
      "InitialHiddenNodeList": [],
      "DialogueTriggerSkipSpecifiedFakeAvatarList": [],
      "OverrideReplaceMaterialKeyList": [],
      "CameraCenterEntityList": [],
      "SpawnConfig": {
        "EntitySpawnConfig": {}
      },
      "TriggerValidGuest": {},
      "Name": "NPC3",
      "RotY": 175.3367,
      "ID": 400003,
      "PosX": -68.648,
      "PosY": -1.012486,
      "PosZ": -59.245
    },
    {
      "NPCID": 12305,
      "ValueSource": {},
      "DialogueGroups": [],
      "ServerInteractVerificationIDList": [],
      "BoardShowList": [],
      "TalkDialogGroupIDList": [],
      "DefaultIdleFreeStyleMotionID": 100040000,
      "InitialHiddenNodeList": [],
      "DialogueTriggerSkipSpecifiedFakeAvatarList": [],
      "OverrideReplaceMaterialKeyList": [],
      "CameraCenterEntityList": [],
      "SpawnConfig": {
        "EntitySpawnConfig": {}
      },
      "TriggerValidGuest": {},
      "Name": "NPC4",
      "RotY": 279.5861,
      "ID": 400004,
      "PosX": -67.765,
      "PosY": -1.012481,
      "PosZ": -59.874
    },
    {
      "NPCID": 13130,
      "ValueSource": {},
      "DialogueGroups": [],
      "ServerInteractVerificationIDList": [],
      "BoardShowList": [],
      "TalkDialogGroupIDList": [],
      "DefaultIdleFreeStyleMotionID": 100010000,
      "InitialHiddenNodeList": [],
      "DialogueTriggerSkipSpecifiedFakeAvatarList": [],
      "OverrideReplaceMaterialKeyList": [],
      "CameraCenterEntityList": [],
      "SpawnConfig": {
        "EntitySpawnConfig": {}
      },
      "TriggerValidGuest": {},
      "Name": "NPC5",
      "RotY": 316.7964,
      "ID": 400005,
      "PosX": -55.973,
      "PosY": -0.885,
      "PosZ": -59.219
    },
    {
      "NPCID": 13319,
      "ValueSource": {},
      "DialogueGroups": [],
      "ServerInteractVerificationIDList": [],
      "BoardShowList": [],
      "TalkDialogGroupIDList": [],
      "DefaultIdleFreeStyleMotionID": 100040000,
      "InitialHiddenNodeList": [],
      "DialogueTriggerSkipSpecifiedFakeAvatarList": [],
      "OverrideReplaceMaterialKeyList": [],
      "CameraCenterEntityList": [],
      "SpawnConfig": {
        "EntitySpawnConfig": {}
      },
      "TriggerValidGuest": {},
      "Name": "NPC6",
      "RotY": 37.29884,
      "ID": 400006,
      "PosX": -56.989,
      "PosY": -0.885,
      "PosZ": -59.46
    },
    {
      "NPCID": 12134,
      "ValueSource": {},
      "DialogueGroups": [],
      "ServerInteractVerificationIDList": [],
      "BoardShowList": [],
      "TalkDialogGroupIDList": [],
      "DefaultIdleFreeStyleMotionID": 100010000,
      "InitialHiddenNodeList": [],
      "DialogueTriggerSkipSpecifiedFakeAvatarList": [],
      "OverrideReplaceMaterialKeyList": [],
      "CameraCenterEntityList": [],
      "SpawnConfig": {
        "EntitySpawnConfig": {}
      },
      "TriggerValidGuest": {},
      "Name": "NPC7",
      "RotY": 228.8708,
      "ID": 400007,
      "PosX": -55.828,
      "PosY": -0.885,
      "PosZ": -58.496
    },
    {
      "NPCID": 1220,
      "ValueSource": {},
      "StaticNPC": true,
      "DialogueGroups": [],
      "ServerInteractVerificationIDList": [],
      "DefaultLookAtMode": "Closed",
      "BoardShowList": [],
      "TalkDialogGroupIDList": [],
      "DefaultIdleFreeStyleMotionID": 312200900,
      "InitialHiddenNodeList": [],
      "DialogueTriggerSkipSpecifiedFakeAvatarList": [],
      "OverrideReplaceMaterialKeyList": [],
      "CameraCenterEntityList": [],
      "SpawnConfig": {
        "EntitySpawnConfig": {}
      },
      "TriggerValidGuest": {},
      "Name": "NPC8",
      "RotY": 184.1752,
      "ID": 400008,
      "PosX": -53.535,
      "PosY": -0.884198,
      "PosZ": -66.862
    },
    {
      "NPCID": 12120,
      "ValueSource": {},
      "DialogueGroups": [],
      "ServerInteractVerificationIDList": [],
      "BoardShowList": [],
      "TalkDialogGroupIDList": [],
      "DefaultIdleFreeStyleMotionID": 100010000,
      "InitialHiddenNodeList": [],
      "DialogueTriggerSkipSpecifiedFakeAvatarList": [],
      "OverrideReplaceMaterialKeyList": [],
      "CameraCenterEntityList": [],
      "SpawnConfig": {
        "EntitySpawnConfig": {}
      },
      "TriggerValidGuest": {},
      "Name": "NPC9",
      "RotY": 300.6575,
      "ID": 400009,
      "PosX": -70.409,
      "PosY": -1.012481,
      "PosZ": -70.014
    },
    {
      "NPCID": 12238,
      "ValueSource": {},
      "DialogueGroups": [],
      "ServerInteractVerificationIDList": [],
      "BoardShowList": [],
      "TalkDialogGroupIDList": [],
      "DefaultIdleFreeStyleMotionID": 100020000,
      "InitialHiddenNodeList": [],
      "DialogueTriggerSkipSpecifiedFakeAvatarList": [],
      "OverrideReplaceMaterialKeyList": [],
      "CameraCenterEntityList": [],
      "SpawnConfig": {
        "EntitySpawnConfig": {}
      },
      "TriggerValidGuest": {},
      "Name": "NPC10",
      "RotY": 225.2123,
      "ID": 400010,
      "PosX": -68.495,
      "PosY": -1.012481,
      "PosZ": -67.202
    },
    {
      "NPCID": 12124,
      "ValueSource": {},
      "DialogueGroups": [],
      "ServerInteractVerificationIDList": [],
      "BoardShowList": [],
      "TalkDialogGroupIDList": [],
      "DefaultIdleFreeStyleMotionID": 100010000,
      "InitialHiddenNodeList": [],
      "DialogueTriggerSkipSpecifiedFakeAvatarList": [],
      "OverrideReplaceMaterialKeyList": [],
      "CameraCenterEntityList": [],
      "SpawnConfig": {
        "EntitySpawnConfig": {}
      },
      "TriggerValidGuest": {},
      "Name": "NPC11",
      "RotY": 337.1824,
      "ID": 400011,
      "PosX": -68.7,
      "PosY": -1.012481,
      "PosZ": -68.235
    }
  ],
  "CrowdList": [],
  "PedestrianList": [],
  "AudienceList": [],
  "SmartObjectList": [],
  "CurveList": [],
  "LittleGameList": []
}